{"blteb761f05745902c5":{"title":"Personalized talks for marketers","title_when_personalized":"","registered_button_text":"","tags":[],"locale":"en-us","ACL":{},"uid":"blteb761f05745902c5","_version":3,"_in_progress":false,"publish_details":[{"environment":"blt5e93b7f53a90f9cd","locale":"en-us","time":"2022-05-22T00:01:48.092Z","user":"blt5aba2c81127bda07","version":3}]},"blt96ad479b218120d3":{"title":"Our conference talks","title_when_personalized":"Personalized talks for you","registered_button_text":"Add to my schedule","tags":[],"locale":"en-us","ACL":{},"uid":"blt96ad479b218120d3","_version":2,"_in_progress":false,"publish_details":[{"environment":"blt5e93b7f53a90f9cd","locale":"en-us","time":"2022-05-08T19:16:43.061Z","user":"blt7905046a9c3c6686","version":2}]},"blt1a326ea1b25e1695":{"title":"Personalized talks for developers","title_when_personalized":"","registered_button_text":"","tags":[],"locale":"en-us","ACL":{},"uid":"blt1a326ea1b25e1695","_version":2,"_in_progress":false,"publish_details":[{"environment":"blt5e93b7f53a90f9cd","locale":"en-us","time":"2022-05-08T19:16:43.063Z","user":"blt7905046a9c3c6686","version":2}]}}